{"data":{"site":{"siteMetadata":{"title":"@nicoespeon's blog","subtitles":{"en":"I write about web development, agile practices and personal organization.","fr":"J’écris sur le développement web, les pratiques agiles et l’organisation personnelle."},"author":{"name":"Nicolas Carlo","twitter":"nicoespeon"},"url":"https://www.nicoespeon.com"}},"markdownRemark":{"id":"9cab5961-7406-5b22-93a7-c5f70175bc94","html":"<p>J’ai présenté ce talk le 29 juin 2016 au <a href=\"http://www.meetup.com/fr-FR/Paris-js/events/232103659/\">meetup Paris.js #57 chez Algolia</a>.</p>\n<div>\n          <div\n            class=\"gatsby-resp-iframe-wrapper\"\n            style=\"padding-bottom: 56.25%; position: relative; height: 0; overflow: hidden;margin-bottom: 1.0725rem\"\n          >\n            <iframe src=\"https://www.youtube-nocookie.com/embed/8fHo34Ah6B0\" frameborder=\"0\" allow=\"accelerometer; autoplay; encrypted-media; gyroscope; picture-in-picture\" allowfullscreen style=\"\n            position: absolute;\n            top: 0;\n            left: 0;\n            width: 100%;\n            height: 100%;\n          \"></iframe>\n          </div>\n          </div>\n<p>Et voici les slides associés qui contiennent pas mal de liens si vous souhaitez approfondir le sujet :</p>\n<div>\n          <div\n            class=\"gatsby-resp-iframe-wrapper\"\n            style=\"padding-bottom: 72.91666666666666%; position: relative; height: 0; overflow: hidden;margin-bottom: 1.0725rem\"\n          >\n            <iframe src=\"https://slides.com/nicoespeon/trello-kanban-cycle-js/embed\" scrolling=\"no\" frameborder=\"0\" webkitallowfullscreen=\"\" mozallowfullscreen=\"\" allowfullscreen style=\"\n            position: absolute;\n            top: 0;\n            left: 0;\n            width: 100%;\n            height: 100%;\n          \"></iframe>\n          </div>\n          </div>\n<p>Le projet est dispo en open-source ici : <a href=\"https://github.com/nicoespeon/trello-kanban-analysis-tool\">https://github.com/nicoespeon/trello-kanban-analysis-tool</a></p>\n<h2 id=\"quelques-retours-post-présentation\"><a href=\"#quelques-retours-post-pr%C3%A9sentation\" aria-hidden=\"true\" class=\"anchor\"><svg aria-hidden=\"true\" height=\"16\" version=\"1.1\" viewBox=\"0 0 16 16\" width=\"16\"><path fill-rule=\"evenodd\" d=\"M4 9h1v1H4c-1.5 0-3-1.69-3-3.5S2.55 3 4 3h4c1.45 0 3 1.69 3 3.5 0 1.41-.91 2.72-2 3.25V8.59c.58-.45 1-1.27 1-2.09C10 5.22 8.98 4 8 4H4c-.98 0-2 1.22-2 2.5S3 9 4 9zm9-3h-1v1h1c1 0 2 1.22 2 2.5S13.98 12 13 12H9c-.98 0-2-1.22-2-2.5 0-.83.42-1.64 1-2.09V6.25c-1.09.53-2 1.84-2 3.25C6 11.31 7.55 13 9 13h4c1.45 0 3-1.69 3-3.5S14.5 6 13 6z\"></path></svg></a>Quelques retours post-présentation</h2>\n<ul>\n<li>Pour commencer, il y a bien un exemple de TodoMVC avec Cycle.js : <a href=\"https://github.com/cyclejs/todomvc-cycle/\">https://github.com/cyclejs/todomvc-cycle/</a></li>\n<li>Concernant le server-side rendering avec Cycle.js : ça se fait bien, toujours avec des streams. Il y a <a href=\"https://github.com/cyclejs/examples/tree/master/isomorphic\">un exemple disponible dans le dépôt de Cycle.js</a>d’ailleurs.</li>\n<li>On m’a posé la question de la différence entre React et Cycle.js (et Elm). Il y a <a href=\"https://www.reddit.com/r/javascript/comments/3zr6i0/conversation_whats_the_core_differences_between/\">une discussion sur le sujet sur reddit</a>.</li>\n</ul>\n<p>Vincent expliquait également il y a quelques mois <a href=\"https://medium.com/@_cmdv_/why-i-chose-to-use-cycle-js-9156173c2752#.kpb0dfkd1\">pourquoi il partait plutôt sur du Cycle.js</a>.</p>\n<p>Quant à mon opinion : ça dépend. Partez sur du React/Redux pour des projets qui partent en production parce-que c’est éprouvé et que la communauté est là. Mais si vous avez du temps libre, essayez voir Cycle.js, vous apprendrez des choses =)</p>","fields":{"tagSlugs":["/fr/tags/cycle-js/","/fr/tags/trello/","/fr/tags/kanban/","/fr/tags/meetup/","/fr/tags/talk/"],"slug":"/fr/2016/07/trello-kanban-cyclejs/"},"timeToRead":1,"frontmatter":{"title":"Trello, Kanban & Cycle.js","tags":["cycle.js","trello","kanban","meetup","talk"],"date":"2016-07-19T00:00:00.000Z","description":"Talk présenté le 29 juin 2016 au meetup Paris.js chez Algolia."}}},"pageContext":{"slug":"/fr/2016/07/trello-kanban-cyclejs/"}}