{"data":{"site":{"siteMetadata":{"title":"@nicoespeon's blog","subtitles":{"en":"I write about web development, agile practices and personal organization.","fr":"J’écris sur le développement web, les pratiques agiles et l’organisation personnelle."},"greetings":{"en":"Hi, I'm Nicolas 👋","fr":"Salut, je suis Nicolas 👋"},"menus":{"en":[{"label":"Articles","path":"/"},{"label":"About me","path":"/about"},{"label":"Projects","path":"/projects"},{"label":"Worth reading","path":"/worth-reading"},{"label":"Talks","path":"/talks"}],"fr":[{"label":"Articles","path":"/fr/"},{"label":"À propos","path":"/fr/about"},{"label":"Projets","path":"/fr/projects"},{"label":"À lire","path":"/fr/worth-reading"},{"label":"Talks","path":"/fr/talks"}]},"author":{"name":"Nicolas Carlo","email":"nicolascarlo.espeon@gmail.com","twitter":"nicoespeon","github":"nicoespeon","linkedin":"nicolas-carlo-095b243b","rss":"/feed.xml"}}},"allMarkdownRemark":{"edges":[{"node":{"fields":{"slug":"/en/2018/06/tdd-with-elixir/","categorySlug":"/categories/web-development/"},"frontmatter":{"title":"TDD with Elixir","date":"2018-06-07T00:00:00.000Z","category":"Web development","description":"A lightning talk I gave at the Montréal Elixir meetup of May 2018."}}},{"node":{"fields":{"slug":"/en/2018/03/i-went-to-montreal-elixir-meetup/","categorySlug":"/categories/web-development/"},"frontmatter":{"title":"So I went to Montreal Elixir meetup","date":"2018-03-23T00:00:00.000Z","category":"Web development","description":"Here is my feedback about how this meetup was, and what you could expect from it."}}}]}},"pageContext":{"tag":"montreal"}}